pytest_htmlx/__init__.py
pytest_htmlx/plugin.py
pytest_htmlx/reporter/__init__.py
pytest_htmlx/reporter/html_reporter.py
pytest_htmlx/reporter/utils.py
pytest_htmlx/reporter/templates/base.html
pytest_htmlx-0.3.4.dist-info/licenses/LICENSE
pytest_htmlx-0.3.4.dist-info/METADATA
pytest_htmlx-0.3.4.dist-info/WHEEL
pytest_htmlx-0.3.4.dist-info/entry_points.txt
pytest_htmlx-0.3.4.dist-info/top_level.txt
pytest_htmlx-0.3.4.dist-info/RECORD
